stacks_image/__init__.py
stacks_image/admin.py
stacks_image/apps.py
stacks_image/models.py
stacks_image/serializers.py
stacks_image/stuff.py
stacks_image/migrations/0001_initial.py
stacks_image/migrations/0002_auto_20150402_1441.py
stacks_image/migrations/0003_auto_20150528_1700.py
stacks_image/migrations/0004_auto_20150528_1701.py
stacks_image/migrations/0005_remove_stacksimagelist_list_name.py
stacks_image/migrations/0006_auto_20150529_2033.py
stacks_image/migrations/0007_stacksimage_attribution.py
stacks_image/migrations/0008_auto_20160119_2202.py
stacks_image/migrations/__init__.py
stacks_image/static/js/stacks_image.js
stacks_image/static/js/vendor/lazyimages/lazyimages.js
stacks_image/static/js/vendor/owl/carousel.js
stacks_image/static/sass/_stacks_image.scss
stacks_image/templates/stacks_image/stacksimage/stacksimage-full_width.html
stacks_image/templates/stacks_image/stacksimage/stacksimage-image_left_content_right.html
stacks_image/templates/stacks_image/stacksimage/stacksimage-image_right_content_left.html
stacks_image/templates/stacks_image/stacksimagelist/stacksimagelist-1up.html
stacks_image/templates/stacks_image/stacksimagelist/stacksimagelist-2up.html
stacks_image/templates/stacks_image/stacksimagelist/stacksimagelist-3up.html
stacks_image/templates/stacks_image/stacksimagelist/stacksimagelist-carousel.html
stacks_image/templates/stacks_image/stacksimagelist/stacksimagelist-gallery.html
stacks_image-0.2.2.dist-info/DESCRIPTION.rst
stacks_image-0.2.2.dist-info/LICENSE.txt
stacks_image-0.2.2.dist-info/METADATA
stacks_image-0.2.2.dist-info/RECORD
stacks_image-0.2.2.dist-info/WHEEL
stacks_image-0.2.2.dist-info/metadata.json
stacks_image-0.2.2.dist-info/top_level.txt
tests/__init__.py
tests/test_settings.py
tests/tests.py
tests/urls.py
